{
  "__type__": "Deck",
  "children": [

  ],
  "crowdanki_uuid": "df844487-8c48-49a6-85d7-e1205df2f61e",
  "deck_config_uuid": "df844487-8c48-49a6-85d7-e1205df2f61e",
  "deck_configurations": [
    {
      "__type__": "DeckConfig",
      "autoplay": true,
      "crowdanki_uuid": "df844487-8c48-49a6-85d7-e1205df2f61e",
      "dyn": false,
      "lapse": {
        "delays": [
          10
        ],
        "leechAction": 0,
        "leechFails": 8,
        "minInt": 1,
        "mult": 0.0
      },
      "maxTaken": 60,
      "name": "Default",
      "new": {
        "bury": true,
        "delays": [
          1,
          10
        ],
        "initialFactor": 2500,
        "ints": [
          1,
          4,
          7
        ],
        "order": 1,
        "perDay": 20,
        "separate": true
      },
      "replayq": true,
      "rev": {
        "bury": true,
        "ease4": 1.3,
        "fuzz": 0.05,
        "ivlFct": 1.0,
        "maxIvl": 36500,
        "minSpace": 1,
        "perDay": 100
      },
      "timer": 0
    }
  ],
  "desc": "",
  "dyn": 0,
  "extendNew": 10,
  "extendRev": 50,
  "media_files": [

  ],
  "mid": "1496861969393",
  "name": "CCNA 200-301",
  "note_models": [
    {
      "__type__": "NoteModel",
      "crowdanki_uuid": "bfa36940-2042-11e9-8b6a-acbc3287506b",
      "css": ".card {\n font-family: arial;\n font-size: 20px;\n text-align: center;\n color: black;\n background-color: white;\n}\n",
      "flds": [
        {
          "font": "Arial",
          "media": [

          ],
          "name": "Front",
          "ord": 0,
          "rtl": false,
          "size": 20,
          "sticky": false
        },
        {
          "font": "Arial",
          "media": [

          ],
          "name": "Back",
          "ord": 1,
          "rtl": false,
          "size": 20,
          "sticky": false
        },
        {
          "font": "Arial",
          "media": [

          ],
          "name": "RerverseCardID",
          "ord": 2,
          "rtl": false,
          "size": 20,
          "sticky": false
        },
        {
          "font": "Arial",
          "media": [

          ],
          "name": "Reference",
          "ord": 3,
          "rtl": false,
          "size": 20,
          "sticky": false
        }
      ],
      "latexPost": "\\end{document}",
      "latexPre": "\\documentclass[12pt]{article}\n\\special{papersize=3in,5in}\n\\usepackage[utf8]{inputenc}\n\\usepackage{amssymb,amsmath}\n\\pagestyle{empty}\n\\setlength{\\parindent}{0in}\n\\begin{document}\n",
      "name": "Basic",
      "req": [
        [
          0,
          "all",
          [
            0
          ]
        ]
      ],
      "sortf": 0,
      "tags": [

      ],
      "tmpls": [
        {
          "afmt": "{{FrontSide}}\n\n<hr id=answer>\n\n{{Back}}\n\n<br/><br/>\nSee: <br/>{{Reference}}",
          "bafmt": "",
          "bqfmt": "",
          "did": null,
          "name": "Card 1",
          "ord": 0,
          "qfmt": "{{Front}}"
        }
      ],
      "type": 0,
      "vers": [

      ]
    }
  ],
  "notes": [
    {
      "__type__": "Note",
      "data": "",
      "fields": [
        "Do you know where this Anki deck originated?",
        "This deck is part of an open collaborative effort started by YYC Net Lab.  This deck is provided free of charge and without warranty.  For updates please see the link below.  If you notice any errors or would like to add some cards please reach out to YYC Net Lab through Github.<br><br>To stop seeing this card click on 'More' in the bottom right and select 'Suspend Card'.",
        "6101100000",
        "https://github.com/yycnetlab/ankidecks"
      ],
      "flags": 0,
      "guid": "6101100000",
      "note_model_uuid": "bfa36940-2042-11e9-8b6a-acbc3287506b",
      "tags": [

      ]
    },
    {
      "__type__": "Note",
      "data": "",
      "fields": [
        "What is UDP port 53 used for?",
        "DNS",
        "6101100002",
        "NetAcad:CCNAv7:ITN:15.1.3"
      ],
      "flags": 0,
      "guid": "6101100001",
      "note_model_uuid": "bfa36940-2042-11e9-8b6a-acbc3287506b",
      "tags": [
        "NetAcad:CCNAv7:ITN:15",
        "Exam:200-301:NotListed"
      ]
    },
    {
      "__type__": "Note",
      "data": "",
      "fields": [
        "What UDP port is used for DNS?",
        "UDP port 53",
        "6101100001",
        "NetAcad:CCNAv7:ITN:15.1.3"
      ],
      "flags": 0,
      "guid": "6101100002",
      "note_model_uuid": "bfa36940-2042-11e9-8b6a-acbc3287506b",
      "tags": [
        "NetAcad:CCNAv7:ITN:15",
        "Exam:200-301:NotListed"
      ]
    }
  ]
}
